[
  {
    "question": "Never have I ever broken a bone.",
    "likes": 0,
    "category": "na"
  },
  {
    "question": "Never have I ever Googled myself.",
    "likes": 0,
    "category": "na"
  },
  {
    "question": "Never have I ever traveled solo.",
    "likes": 0,
    "category": "na"
  },
  {
    "question": "Never have I ever seen a ghost.",
    "likes": 0,
    "category": "na"
  },
  {
    "question": "Never have I ever toilet-papered someone's house.",
    "likes": 0,
    "category": "na"
  },
  {
    "question": "Never have I ever laughed so hard I spat out my drink.",
    "likes": 0,
    "category": "na"
  },
  {
    "question": "Never have I ever pretended to be on the phone.",
    "likes": 0,
    "category": "na"
  },
  {
    "question": "Never have I ever met a celebrity.",
    "likes": 0,
    "category": "na"
  },
  {
    "question": "Never have I ever sleepwalked.",
    "likes": 0,
    "category": "na"
  },
  {
    "question": "Never have I ever read an entire book in a day.",
    "likes": 0,
    "category": "na"
  },
  {
    "question": "Never have I ever gone to a party I wasn\u2019t invited to.",
    "likes": 0,
    "category": "na"
  },
  {
    "question": "Never have I ever stayed up all night.",
    "likes": 0,
    "category": "na"
  },
  {
    "question": "Never have I ever sent a cute morning text.",
    "likes": 0,
    "category": "na"
  },
  {
    "question": "Never have I ever broken someone\u2019s heart.",
    "likes": 0,
    "category": "na"
  },
  {
    "question": "Never have I ever given a massage.",
    "likes": 0,
    "category": "na"
  },
  {
    "question": "Never have I ever fallen out of love.",
    "likes": 0,
    "category": "na"
  },
  {
    "question": "Never have I ever received a love letter.",
    "likes": 0,
    "category": "na"
  },
  {
    "question": "Never have I ever used a pick-up line.",
    "likes": 0,
    "category": "na"
  },
  {
    "question": "Never have I ever dated someone for their looks.",
    "likes": 0,
    "category": "na"
  },
  {
    "question": "Never have I ever left someone on \u201cread\u201d.",
    "likes": 0,
    "category": "na"
  },
  {
    "question": "Never have I ever regretted something.",
    "likes": 0,
    "category": "na"
  },
  {
    "question": "Never have I ever wished I was famous.",
    "likes": 0,
    "category": "na"
  },
  {
    "question": "Never have I ever helped a stranger.",
    "likes": 0,
    "category": "na"
  },
  {
    "question": "Never have I ever gotten bored of a relationship.",
    "likes": 0,
    "category": "na"
  },
  {
    "question": "Never have I ever broken a promise.",
    "likes": 0,
    "category": "na"
  },
  {
    "question": "Never have I ever fallen in love with a fictional character.",
    "likes": 0,
    "category": "na"
  },
  {
    "question": "Never have I ever felt nervous in front of someone in this room.",
    "likes": 0,
    "category": "na"
  },
  {
    "question": "Never have I ever wanted to go skydiving.",
    "likes": 0,
    "category": "na"
  },
  {
    "question": "Never have I ever fallen asleep at school.",
    "likes": 0,
    "category": "na"
  },
  {
    "question": "Never have I ever dyed my hair.",
    "likes": 0,
    "category": "na"
  },
  {
    "question": "Never have I ever read an entire book in a day.",
    "likes": 0,
    "category": "na"
  },
  {
    "question": "Never have I ever seen an alligator in real life.",
    "likes": 0,
    "category": "na"
  },
  {
    "question": "Never have I ever re-gifted a gift.",
    "likes": 0,
    "category": "na"
  },
  {
    "question": "Never have I ever sleepwalked.",
    "likes": 0,
    "category": "na"
  },
  {
    "question": "Never have I ever gone snowboarding.",
    "likes": 0,
    "category": "na"
  },
  {
    "question": "Never have I ever been awake for 48 hours (or more) straight.",
    "likes": 0,
    "category": "na"
  },
  {
    "question": "Never have I ever broken up with someone in a way I regret.",
    "likes": 0,
    "category": "na"
  },
  { "question": "Never have I ever fainted.", "likes": 0, "category": "na" },
  {
    "question": "Never have I ever had a fight with a significant other in public.",
    "likes": 0,
    "category": "na"
  },
  {
    "question": "Never have I ever knowingly spread a rumour.",
    "likes": 0,
    "category": "na"
  },
  {
    "question": "Never have I ever cried at school.",
    "likes": 0,
    "category": "na"
  },
  {
    "question": "Never have I ever been somewhere I was sure was haunted.",
    "likes": 0,
    "category": "na"
  },
  {
    "question": "Never have I ever cut my own hair.",
    "likes": 0,
    "category": "na"
  },
  {
    "question": "Never have I ever lied to get out of plans with friends.",
    "likes": 0,
    "category": "na"
  },
  {
    "question": "Never have I ever had a crush on a friend's sibling.",
    "likes": 0,
    "category": "na"
  },
  {
    "question": "Never have I ever eaten a tub of ice cream.",
    "likes": 0,
    "category": "na"
  },
  {
    "question": "Never have I ever gone commando.",
    "likes": 0,
    "category": "na"
  },
  {
    "question": "Never have I ever shaved my head.",
    "likes": 0,
    "category": "na"
  },
  {
    "question": "Never have I ever gotten a tattoo.",
    "likes": 0,
    "category": "na"
  },
  {
    "question": "Never have I ever broken a bone.",
    "likes": 0,
    "category": "na"
  },
  {
    "question": "Never have I ever been to a hen party or stag party.",
    "likes": 0,
    "category": "na"
  },
  {
    "question": "Never have I ever gotten heated during a family game night.",
    "likes": 0,
    "category": "na"
  },
  {
    "question": "Never have I ever met a celebrity.",
    "likes": 0,
    "category": "na"
  },
  {
    "question": "Never have I ever had a surprise party thrown for me.",
    "likes": 0,
    "category": "na"
  },
  {
    "question": "Never have I ever traveled solo.",
    "likes": 0,
    "category": "na"
  },
  {
    "question": "Never have I ever eaten whipped cream straight from the can.",
    "likes": 0,
    "category": "na"
  },
  {
    "question": "Never have I ever auditioned for a reality TV show.",
    "likes": 0,
    "category": "na"
  },
  {
    "question": "Never have I ever told my parents I was staying at a friend's house but was really somewhere else.",
    "likes": 0,
    "category": "na"
  },
  {
    "question": "Never have I ever been to a psychic.",
    "likes": 0,
    "category": "na"
  },
  {
    "question": "Never have I ever lived alone.",
    "likes": 0,
    "category": "na"
  },
  {
    "question": "Never have I ever sang karaoke.",
    "likes": 0,
    "category": "na"
  },
  {
    "question": "Never have I ever stayed overnight in the hospital.",
    "likes": 0,
    "category": "na"
  },
  {
    "question": "Never have I ever deleted a post because it didn't get enough likes.",
    "likes": 0,
    "category": "na"
  },
  {
    "question": "Never have I ever stayed up all night.",
    "likes": 0,
    "category": "na"
  },
  {
    "question": "Never have I ever been on a cruise.",
    "likes": 0,
    "category": "na"
  },
  { "question": "Never have I ever lost a bet.", "likes": 0, "category": "na" },
  {
    "question": "Never have I ever gotten in a car accident.",
    "likes": 0,
    "category": "na"
  },
  {
    "question": "Never have I ever ridden a motorcycle.",
    "likes": 0,
    "category": "na"
  },
  {
    "question": "Never have I ever pretended to be sick to get out of school.",
    "likes": 0,
    "category": "na"
  },
  {
    "question": "Never have I ever watched an entire television series in a day.",
    "likes": 0,
    "category": "na"
  },
  {
    "question": "Never have I ever said \u201cI love you\u201d to someone by accident.",
    "likes": 0,
    "category": "na"
  },
  {
    "question": "Never have I ever walked in on my parents having sex.",
    "likes": 0,
    "category": "na"
  },
  {
    "question": "Never have I ever lied while playing this game.",
    "likes": 0,
    "category": "na"
  },
  {
    "question": "Never have I ever Googled myself.",
    "likes": 0,
    "category": "na"
  },
  {
    "question": "Never have I ever had a pet name for a significant other.",
    "likes": 0,
    "category": "na"
  },
  {
    "question": "Never have I ever been given a pet name by a significant other.",
    "likes": 0,
    "category": "na"
  },
  {
    "question": "Never have I ever had a dirty dream about a super unexpected person.",
    "likes": 0,
    "category": "na"
  },
  {
    "question": "Never have I ever been accused of sharing too much on social media.",
    "likes": 0,
    "category": "na"
  },
  {
    "question": "Never have I ever created a fake social media account.",
    "likes": 0,
    "category": "na"
  },
  {
    "question": "Never have I ever run out of petrol while driving.",
    "likes": 0,
    "category": "na"
  },
  {
    "question": "Never have I ever gone to a party I wasn\u2019t invited to.",
    "likes": 0,
    "category": "na"
  },
  {
    "question": "Never have I ever dated someone super annoying only because they\u2019re cute.",
    "likes": 0,
    "category": "na"
  },
  {
    "question": "Never have I ever lied on a first date.",
    "likes": 0,
    "category": "na"
  },
  {
    "question": "Never have I ever used someone else's toothbrush.",
    "likes": 0,
    "category": "na"
  },
  {
    "question": "Never have I ever pretended to be on the phone.",
    "likes": 0,
    "category": "na"
  },
  {
    "question": "Never have I ever enjoyed a smell I\u2019m supposed to find gross.",
    "likes": 0,
    "category": "na"
  },
  {
    "question": "Never have I ever been on TV for an embarrassing reason.",
    "likes": 0,
    "category": "na"
  },
  {
    "question": "Never have I ever gone several days without showering.",
    "likes": 0,
    "category": "na"
  },
  {
    "question": "Never have I ever turned my underwear inside out so I don\u2019t have to wash it.",
    "likes": 0,
    "category": "na"
  },
  {
    "question": "Never have I ever lied about what I was doing on social media.",
    "likes": 0,
    "category": "na"
  },
  {
    "question": "Never have I ever farted in front of a significant other.",
    "likes": 0,
    "category": "na"
  },
  {
    "question": "Never have I ever peed in the shower.",
    "likes": 0,
    "category": "na"
  },
  {
    "question": "Never have I ever peed in a pool.",
    "likes": 0,
    "category": "na"
  },
  {
    "question": "Never have I ever eaten a tub of ice cream.",
    "likes": 0,
    "category": "na"
  },
  {
    "question": "Never have I ever cheated in a board game.",
    "likes": 0,
    "category": "na"
  },
  {
    "question": "Never have I ever cheated in a card game.",
    "likes": 0,
    "category": "na"
  },
  {
    "question": "Never have I ever screamed during a scary movie.",
    "likes": 0,
    "category": "na"
  },
  {
    "question": "Never have I ever laughed so hard I spit out my drink.",
    "likes": 0,
    "category": "na"
  },
  {
    "question": "Never have I ever been sent to the head teacher's office.",
    "likes": 0,
    "category": "na"
  },
  {
    "question": "Never have I ever clogged a toilet.",
    "likes": 0,
    "category": "na"
  },
  {
    "question": "Never have I ever toilet-papered someone's house.",
    "likes": 0,
    "category": "na"
  },
  {
    "question": "Never have I ever worn something I took out of the dirty laundry.",
    "likes": 0,
    "category": "na"
  },
  {
    "question": "Never have I ever vomited after a roller coaster ride.",
    "likes": 0,
    "category": "na"
  },
  {
    "question": "Never have I ever found a dumb excuse to text an ex.",
    "likes": 0,
    "category": "na"
  },
  {
    "question": "Never have I ever fallen in love at first sight.",
    "likes": 0,
    "category": "na"
  },
  {
    "question": "Never have I ever kissed someone I just met.",
    "likes": 0,
    "category": "na"
  },
  {
    "question": "Never have I ever kept a crush a secret from people in this room.",
    "likes": 0,
    "category": "na"
  },
  {
    "question": "Never have I ever been in love with someone without them knowing.",
    "likes": 0,
    "category": "na"
  },
  {
    "question": "Never have I ever been in an open relationship.",
    "likes": 0,
    "category": "na"
  },
  {
    "question": "Never have I ever fantasised about getting back with an ex.",
    "likes": 0,
    "category": "na"
  },
  {
    "question": "Never have I ever helped a friend lie by being their alibi.",
    "likes": 0,
    "category": "na"
  },
  {
    "question": "Never have I ever seriously thought about marrying someone.",
    "likes": 0,
    "category": "na"
  },
  {
    "question": "Never have I ever had a totally online relationship.",
    "likes": 0,
    "category": "na"
  },
  {
    "question": "Never have I ever flirted just to get something I wanted.",
    "likes": 0,
    "category": "na"
  },
  {
    "question": "Never have I ever tried guessing someone\u2019s password.",
    "likes": 0,
    "category": "na"
  },
  {
    "question": "Never have I ever been caught lying.",
    "likes": 0,
    "category": "na"
  },
  {
    "question": "Never have I ever intentionally started a fight between other people.",
    "likes": 0,
    "category": "na"
  },
  {
    "question": "Never have I ever dated more than one person at once.",
    "likes": 0,
    "category": "na"
  },
  {
    "question": "Never have I ever spent money that wasn\u2019t mine to spend.",
    "likes": 0,
    "category": "na"
  },
  {
    "question": "Never have I ever had a relationship last less than a month.",
    "likes": 0,
    "category": "na"
  },
  {
    "question": "Never have I ever had a relationship last longer than a year",
    "likes": 0,
    "category": "na"
  },
  {
    "question": "Never have I ever dated someone older than me.",
    "likes": 0,
    "category": "na"
  },
  {
    "question": "Never have I ever dated someone younger than me.",
    "likes": 0,
    "category": "na"
  },
  {
    "question": "Never have I ever broken the law.",
    "likes": 0,
    "category": "na"
  },
  {
    "question": "Never have I ever been to a nude beach.",
    "likes": 0,
    "category": "na"
  },
  { "question": "Never have I stood a date up.", "likes": 0, "category": "na" },
  {
    "question": "Never have I ever stayed in a relationship that I really wasn\u2019t feeling.",
    "likes": 0,
    "category": "na"
  },
  {
    "question": "Never have I ever given someone a fake phone number.",
    "likes": 0,
    "category": "na"
  },
  {
    "question": "Never have I ever lied to someone in this room.",
    "likes": 0,
    "category": "na"
  },
  {
    "question": "Never have I ever broken up with someone over text.",
    "likes": 0,
    "category": "na"
  },
  {
    "question": "Never have I ever had a crush on a significant other\u2019s best friend.",
    "likes": 0,
    "category": "na"
  },
  { "question": "Never have I ever shoplifted.", "likes": 0, "category": "na" },
  {
    "question": "Never have I ever seen a ghost.",
    "likes": 0,
    "category": "na"
  },
  {
    "question": "Never have I told a secret I wasn\u2019t supposed to share.",
    "likes": 0,
    "category": "na"
  },
  {
    "question": "Never have I ever had a negative bank account balance.",
    "likes": 0,
    "category": "na"
  },
  {
    "question": "Never have I ever cheated on a test.",
    "likes": 0,
    "category": "na"
  },
  {
    "question": "Never have I ever used a dating app.",
    "likes": 0,
    "category": "na"
  },
  {
    "question": "Never have I ever smoked a cigarette.",
    "likes": 0,
    "category": "na"
  },
  {
    "question": "Never have I ever snooped through someone's phone.",
    "likes": 0,
    "category": "na"
  },
  {
    "question": "Never have I ever snuck into a movie theatre.",
    "likes": 0,
    "category": "na"
  },
  {
    "question": "Never have I ever gotten into a physical fight.",
    "likes": 0,
    "category": "na"
  },
  {
    "question": "Never have I ever dined and dashed.",
    "likes": 0,
    "category": "na"
  },
  {
    "question": "Never have I ever ghosted someone.",
    "likes": 0,
    "category": "na"
  },
  {
    "question": "Never have I ever gotten a speeding ticket",
    "likes": 0,
    "category": "na"
  },
  {
    "question": "Never have I ever gone on a blind date.",
    "likes": 0,
    "category": "na"
  },
  {
    "question": "Never have I ever looked up an ex on social media.",
    "likes": 0,
    "category": "na"
  },
  {
    "question": "Never have I ever been hungover.",
    "likes": 0,
    "category": "na"
  },
  {
    "question": "Never have I ever broken a bone.",
    "likes": 0,
    "category": "na"
  },
  {
    "question": "Never have I ever Googled myself.",
    "likes": 0,
    "category": "na"
  },
  {
    "question": "Never have I ever traveled solo.",
    "likes": 0,
    "category": "na"
  },
  {
    "question": "Never have I ever seen a ghost.",
    "likes": 0,
    "category": "na"
  },
  {
    "question": "Never have I ever toilet-papered someone's house.",
    "likes": 0,
    "category": "na"
  },
  {
    "question": "Never have I ever laughed so hard I spat out my drink.",
    "likes": 0,
    "category": "na"
  },
  {
    "question": "Never have I ever pretended to be on the phone.",
    "likes": 0,
    "category": "na"
  },
  {
    "question": "Never have I ever met a celebrity.",
    "likes": 0,
    "category": "na"
  },
  {
    "question": "Never have I ever sleepwalked.",
    "likes": 0,
    "category": "na"
  },
  {
    "question": "Never have I ever read an entire book in a day.",
    "likes": 0,
    "category": "na"
  },
  {
    "question": "Never have I ever gone to a party I wasn\u2019t invited to.",
    "likes": 0,
    "category": "na"
  },
  {
    "question": "Never have I ever sang karaoke",
    "likes": 0,
    "category": "na"
  },
  {
    "question": "Never have I ever broken a bone",
    "likes": 0,
    "category": "na"
  },
  { "question": "Never have I ever lived alone", "likes": 0, "category": "na" },
  {
    "question": "Never have I ever been on a yacht",
    "likes": 0,
    "category": "na"
  },
  { "question": "Never have I ever been on TV", "likes": 0, "category": "na" },
  {
    "question": "Never have I ever been on a blind date",
    "likes": 0,
    "category": "na"
  },
  {
    "question": "Never have I ever lied to law enforcement",
    "likes": 0,
    "category": "na"
  },
  {
    "question": "Never have I ever broken up with someone",
    "likes": 0,
    "category": "na"
  },
  {
    "question": "Never have I ever gotten seriously hungover",
    "likes": 0,
    "category": "na"
  },
  {
    "question": "Never have I ever used someone else\u2019s toothbrush",
    "likes": 0,
    "category": "na"
  },
  {
    "question": "Never have I ever clogged somebody else\u2019s toilet",
    "likes": 0,
    "category": "na"
  },
  {
    "question": "Never have I ever fallen asleep in public",
    "likes": 0,
    "category": "na"
  },
  {
    "question": "Never have I ever kissed someone in public",
    "likes": 0,
    "category": "na"
  },
  {
    "question": "Never have I ever fought in public",
    "likes": 0,
    "category": "na"
  },
  {
    "question": "Never have I ever dined and dashed",
    "likes": 0,
    "category": "na"
  },
  {
    "question": "Never have I ever won the lottery",
    "likes": 0,
    "category": "na"
  },
  {
    "question": "Never have I ever had to go to court",
    "likes": 0,
    "category": "na"
  },
  {
    "question": "Never have I ever lied to a boss",
    "likes": 0,
    "category": "na"
  },
  {
    "question": "Never have I ever regifted a gift",
    "likes": 0,
    "category": "na"
  },
  {
    "question": "Never have I ever trolled someone on social media",
    "likes": 0,
    "category": "na"
  },
  {
    "question": "Never have I ever climbed out of a window",
    "likes": 0,
    "category": "na"
  },
  {
    "question": "Never have I ever snooped through someone\u2019s stuff",
    "likes": 0,
    "category": "na"
  },
  {
    "question": "Never have I ever tried marijuana",
    "likes": 0,
    "category": "na"
  },
  {
    "question": "Never have I ever ate an entire pizza by myself",
    "likes": 0,
    "category": "na"
  },
  {
    "question": "Never have I ever saved a life",
    "likes": 0,
    "category": "na"
  },
  {
    "question": "Never have I ever made a speech in front of 100 people or more",
    "likes": 0,
    "category": "na"
  },
  {
    "question": "Never have I ever left someone on read",
    "likes": 0,
    "category": "na"
  },
  {
    "question": "Never have I ever believed something was haunted",
    "likes": 0,
    "category": "na"
  },
  {
    "question": "Never have I ever participated in a protest",
    "likes": 0,
    "category": "na"
  },
  {
    "question": "Never have I ever had sleep paralysis",
    "likes": 0,
    "category": "na"
  },
  {
    "question": "Never have I ever been the alibi for a lying friend",
    "likes": 0,
    "category": "na"
  },
  {
    "question": "Never have I ever pulled an all-nighter",
    "likes": 0,
    "category": "na"
  },
  { "question": "Never have I ever role-played", "likes": 0, "category": "na" },
  {
    "question": "Never have I ever regretted an apology",
    "likes": 0,
    "category": "na"
  },
  {
    "question": "Never have I ever pretended I was sick for attention",
    "likes": 0,
    "category": "na"
  },
  {
    "question": "Never have I ever disliked something that I cooked",
    "likes": 0,
    "category": "na"
  },
  {
    "question": "Never have I ever deleted a post on social media because it didn\u2019t get enough likes",
    "likes": 0,
    "category": "na"
  },
  {
    "question": "Never have I ever spent more than $100 on a top",
    "likes": 0,
    "category": "na"
  },
  {
    "question": "Never have I ever thrown a drink at someone",
    "likes": 0,
    "category": "na"
  },
  {
    "question": "Never have I ever maxed out a credit card",
    "likes": 0,
    "category": "na"
  },
  {
    "question": "Never have I ever pretended to be sick to get out of something",
    "likes": 0,
    "category": "na"
  },
  {
    "question": "Never have I ever stood up a date",
    "likes": 0,
    "category": "na"
  },
  {
    "question": "Never have I ever ghosted someone",
    "likes": 0,
    "category": "na"
  },
  {
    "question": "Never have I ever tried hard drugs.",
    "likes": 0,
    "category": "na"
  },
  {
    "question": "Never have I ever fallen asleep in public.",
    "likes": 0,
    "category": "na"
  },
  {
    "question": "Never have I ever played a musical instrument.",
    "likes": 0,
    "category": "na"
  },
  {
    "question": "Never have I ever gone snowboarding.",
    "likes": 0,
    "category": "na"
  },
  {
    "question": "Never have I ever gone skiing.",
    "likes": 0,
    "category": "na"
  },
  {
    "question": "Never have I ever learned a foreign language.",
    "likes": 0,
    "category": "na"
  },
  {
    "question": "Never have I ever sent a stranger a drink.",
    "likes": 0,
    "category": "na"
  },
  {
    "question": "Never have I ever accepted a drink from a stranger.",
    "likes": 0,
    "category": "na"
  },
  {
    "question": "Never have I ever lied about my income.",
    "likes": 0,
    "category": "na"
  },
  {
    "question": "Never have I ever texted or taken a call at the movies.",
    "likes": 0,
    "category": "na"
  },
  {
    "question": "Never have I ever convinced a friend to dump a partner.",
    "likes": 0,
    "category": "na"
  },
  {
    "question": "Never have I ever convinced a partner to dump a friend.",
    "likes": 0,
    "category": "na"
  },
  {
    "question": "Never have I ever been someone else's alibi.",
    "likes": 0,
    "category": "na"
  },
  {
    "question": "Never have I ever hopped a turnstile.",
    "likes": 0,
    "category": "na"
  },
  {
    "question": "Never have I ever snitched on someone else at work.",
    "likes": 0,
    "category": "na"
  },
  {
    "question": "Never have I ever won more than $50 gambling.",
    "likes": 0,
    "category": "na"
  },
  {
    "question": "Never have I ever lost more than $50 gambling.",
    "likes": 0,
    "category": "na"
  },
  {
    "question": "Never have I ever lied about my age",
    "likes": 0,
    "category": "na"
  },
  {
    "question": "Never have I ever had a lucid dream.",
    "likes": 0,
    "category": "na"
  },
  {
    "question": "Never have I ever campaigned for a political candidate.",
    "likes": 0,
    "category": "na"
  },
  {
    "question": "Never have I ever lied to a law enforcement officer.",
    "likes": 0,
    "category": "na"
  },
  {
    "question": "Never have I ever been a maid of honor.",
    "likes": 0,
    "category": "na"
  },
  {
    "question": "Never have I ever been a best man.",
    "likes": 0,
    "category": "na"
  },
  {
    "question": "Never have I ever cut in line on purpose.",
    "likes": 0,
    "category": "na"
  },
  {
    "question": "Never have I ever held a grudge longer than a year.",
    "likes": 0,
    "category": "na"
  },
  {
    "question": "Never have I ever blabbed something I swore to secrecy.",
    "likes": 0,
    "category": "na"
  },
  {
    "question": "Never have I ever ruined someone else's vacation.",
    "likes": 0,
    "category": "na"
  },
  {
    "question": "Never have I ever chipped a tooth.",
    "likes": 0,
    "category": "na"
  },
  {
    "question": "Never have I ever tried a fad diet.",
    "likes": 0,
    "category": "na"
  },
  {
    "question": "Never have I ever cut my own hair.",
    "likes": 0,
    "category": "na"
  },
  {
    "question": "Never have I ever been awake for 24 straight hours or more.",
    "likes": 0,
    "category": "na"
  },
  {
    "question": "Never have I ever accidentally said \"I love you\" to someone.",
    "likes": 0,
    "category": "na"
  },
  {
    "question": "Never have I ever spent an entire day watching reality TV.",
    "likes": 0,
    "category": "na"
  },
  {
    "question": "Never have I ever thought a cartoon character was hot.",
    "likes": 0,
    "category": "na"
  },
  {
    "question": "Never have I ever Googled someone before a date.",
    "likes": 0,
    "category": "na"
  },
  {
    "question": "Never have I ever re-gifted something",
    "likes": 0,
    "category": "na"
  },
  {
    "question": "Never have I ever dated a musician.",
    "likes": 0,
    "category": "na"
  },
  {
    "question": "Never have I ever had a wardrobe malfunction.",
    "likes": 0,
    "category": "na"
  },
  {
    "question": "Never have I ever run for my life.",
    "likes": 0,
    "category": "na"
  },
  {
    "question": "Never have I ever been in a talent show.",
    "likes": 0,
    "category": "na"
  },
  {
    "question": "Never have I ever gotten stitches.",
    "likes": 0,
    "category": "na"
  },
  {
    "question": "Never have I ever set something on fire while cooking.",
    "likes": 0,
    "category": "na"
  },
  {
    "question": "Never have I ever set a friend up on a date.",
    "likes": 0,
    "category": "na"
  },
  {
    "question": "Never have I ever done a \"drive-by\" of an ex or crush's house.",
    "likes": 0,
    "category": "na"
  },
  {
    "question": "Never have I ever danced on a table.",
    "likes": 0,
    "category": "na"
  },
  {
    "question": "Never have I ever had frostbite.",
    "likes": 0,
    "category": "na"
  },
  {
    "question": "Never have I ever had a blistering sunburn.",
    "likes": 0,
    "category": "na"
  },
  {
    "question": "Never have I ever gotten sick on a date.",
    "likes": 0,
    "category": "na"
  },
  {
    "question": "Never have I ever had food poisoning.",
    "likes": 0,
    "category": "na"
  },
  {
    "question": "Never have I ever purposely given someone bad advice.",
    "likes": 0,
    "category": "na"
  },
  {
    "question": "Never have I ever heckled a live performance.",
    "likes": 0,
    "category": "na"
  },
  {
    "question": "Never have I ever had surgery.",
    "likes": 0,
    "category": "na"
  },
  {
    "question": "Never have I ever hit a parked car.",
    "likes": 0,
    "category": "na"
  },
  {
    "question": "Never have I ever thrown someone else a surprise party.",
    "likes": 0,
    "category": "na"
  },
  {
    "question": "Never have I ever had a surprise party thrown for me.",
    "likes": 0,
    "category": "na"
  },
  {
    "question": "Never have I ever adjusted myself in public.",
    "likes": 0,
    "category": "na"
  },
  {
    "question": "Never have I ever gone commando.",
    "likes": 0,
    "category": "na"
  },
  {
    "question": "Never have I ever worn a wig or extensions.",
    "likes": 0,
    "category": "na"
  },
  {
    "question": "Never have I ever dressed in drag.",
    "likes": 0,
    "category": "na"
  },
  {
    "question": "Never have I ever been dumpster diving.",
    "likes": 0,
    "category": "na"
  },
  {
    "question": "Never have I ever had surgery.",
    "likes": 0,
    "category": "na"
  },
  {
    "question": "Never have I ever parked in a handicap spot.",
    "likes": 0,
    "category": "na"
  },
  {
    "question": "Never have I ever second-guessed a relationship.",
    "likes": 0,
    "category": "na"
  },
  { "question": "Never have I ever had braces.", "likes": 0, "category": "na" },
  {
    "question": "Never have I ever had a cavity.",
    "likes": 0,
    "category": "na"
  },
  { "question": "Never have I ever hitchhiked.", "likes": 0, "category": "na" },
  {
    "question": "Never have I ever picked up a hitchhiker.",
    "likes": 0,
    "category": "na"
  },
  {
    "question": "Never have I ever changed a tire.",
    "likes": 0,
    "category": "na"
  },
  {
    "question": "Never have I ever lied about my relationship status.",
    "likes": 0,
    "category": "na"
  },
  {
    "question": "Never have I ever second-guessed a relationship.",
    "likes": 0,
    "category": "na"
  },
  { "question": "Never have I ever had braces.", "likes": 0, "category": "na" },
  {
    "question": "Never have I ever had a cavity.",
    "likes": 0,
    "category": "na"
  },
  { "question": "Never have I ever hitchhiked.", "likes": 0, "category": "na" },
  {
    "question": "Never have I ever picked up a hitchhiker.",
    "likes": 0,
    "category": "na"
  },
  {
    "question": "Never have I ever changed a tire.",
    "likes": 0,
    "category": "na"
  },
  {
    "question": "Never have I ever lied about my relationship status.",
    "likes": 0,
    "category": "na"
  },
  {
    "question": "Never have I ever fallen in love at first sight.",
    "likes": 0,
    "category": "na"
  },
  {
    "question": "Never have I ever sneezed on a stranger.",
    "likes": 0,
    "category": "na"
  },
  {
    "question": "Never have I ever thrown up in public.",
    "likes": 0,
    "category": "na"
  },
  {
    "question": "Never have I ever wished I had kids.",
    "likes": 0,
    "category": "na"
  },
  {
    "question": "Never have I ever drank an entire bottle of wine.",
    "likes": 0,
    "category": "na"
  },
  {
    "question": "Never have I ever witnessed a crime.",
    "likes": 0,
    "category": "na"
  },
  {
    "question": "Never have I ever ridden a horse.",
    "likes": 0,
    "category": "na"
  },
  { "question": "Never have I ever fainted.", "likes": 0, "category": "na" },
  {
    "question": "Never have I ever clogged a toilet.",
    "likes": 0,
    "category": "na"
  },
  {
    "question": "Never have I ever been camping.",
    "likes": 0,
    "category": "na"
  },
  {
    "question": "Never have I ever donated blood.",
    "likes": 0,
    "category": "na"
  },
  {
    "question": "Never have I ever gotten in a physical fight.",
    "likes": 0,
    "category": "na"
  },
  {
    "question": "Never have I ever lurked my partner's ex on social media.",
    "likes": 0,
    "category": "na"
  },
  {
    "question": "Never have I ever shared a news story without reading past the headline.",
    "likes": 0,
    "category": "na"
  },
  {
    "question": "Never have I ever been fired from a job.",
    "likes": 0,
    "category": "na"
  },
  {
    "question": "Never have I ever fought with a partner in public.",
    "likes": 0,
    "category": "na"
  },
  {
    "question": "Never have I ever waited tables.",
    "likes": 0,
    "category": "na"
  },
  {
    "question": "Never have I ever worked retail.",
    "likes": 0,
    "category": "na"
  },
  {
    "question": "Never have I ever run a red light.",
    "likes": 0,
    "category": "na"
  },
  {
    "question": "Never have I ever been cheated on.",
    "likes": 0,
    "category": "na"
  },
  {
    "question": "Never have I ever been the subject of a rumor that wasn't true.",
    "likes": 0,
    "category": "na"
  },
  {
    "question": "Never have I ever spread a rumor I knew wasn't true.",
    "likes": 0,
    "category": "na"
  },
  {
    "question": "Never have I ever cried in public.",
    "likes": 0,
    "category": "na"
  },
  {
    "question": "Never have I ever performed onstage.",
    "likes": 0,
    "category": "na"
  },
  {
    "question": "Never have I ever laughed at a funeral.",
    "likes": 0,
    "category": "na"
  },
  {
    "question": "Never have I ever given someone a fake phone number.",
    "likes": 0,
    "category": "na"
  },
  {
    "question": "Never have I ever left a mean YouTube comment.",
    "likes": 0,
    "category": "na"
  },
  {
    "question": "Never have I ever trolled a stranger online.",
    "likes": 0,
    "category": "na"
  },
  {
    "question": "Never have I ever been in a police car.",
    "likes": 0,
    "category": "na"
  },
  {
    "question": "Never have I ever called the cops on someone else.",
    "likes": 0,
    "category": "na"
  },
  { "question": "Never have I ever shoplifted.", "likes": 0, "category": "na" },
  {
    "question": "Never have I ever gone bungee jumping.",
    "likes": 0,
    "category": "na"
  },
  {
    "question": "Never have I ever left a negative Yelp review.",
    "likes": 0,
    "category": "na"
  },
  {
    "question": "Never have I ever went more than three days without showering.",
    "likes": 0,
    "category": "na"
  },
  {
    "question": "Never have I ever gone more than 20 mph over the speed limit.",
    "likes": 0,
    "category": "na"
  },
  {
    "question": "Never have I ever had a paranormal experience.",
    "likes": 0,
    "category": "na"
  },
  {
    "question": "Never have I ever gone skydiving.",
    "likes": 0,
    "category": "na"
  },
  {
    "question": "Never have I ever spent a night in jail.",
    "likes": 0,
    "category": "na"
  },
  {
    "question": "Never have I ever dined and ditched.",
    "likes": 0,
    "category": "na"
  },
  {
    "question": "Never have I ever lurked my ex on social media.",
    "likes": 0,
    "category": "na"
  },
  {
    "question": "Never have I ever re-gifted something.",
    "likes": 0,
    "category": "na"
  },
  {
    "question": "Never have I ever pretended to be someone else online.",
    "likes": 0,
    "category": "na"
  },
  {
    "question": "Never have I ever gone skydiving.",
    "likes": 0,
    "category": "na"
  },
  {
    "question": "Never have I ever cooked an entire four-course meal.",
    "likes": 0,
    "category": "na"
  },
  {
    "question": "Never have I ever left the country.",
    "likes": 0,
    "category": "na"
  },
  {
    "question": "Never have I ever gotten a tattoo.",
    "likes": 0,
    "category": "na"
  },
  {
    "question": "Never have I ever had a surprise party thrown for me.",
    "likes": 0,
    "category": "na"
  },
  {
    "question": "Never have I ever cried because my team lost.",
    "likes": 0,
    "category": "na"
  },
  { "question": "Never have I ever quit a job.", "likes": 0, "category": "na" },
  {
    "question": "Never have I ever been on an airplane.",
    "likes": 0,
    "category": "na"
  },
  {
    "question": "Never have I ever won an award at work.",
    "likes": 0,
    "category": "na"
  },
  {
    "question": "Never have I ever read an entire book in one sitting.",
    "likes": 0,
    "category": "na"
  },
  {
    "question": "Never have I ever roller-skated or rollerbladed.",
    "likes": 0,
    "category": "na"
  },
  {
    "question": "Never have I ever \"ghosted\" someone I was dating.",
    "likes": 0,
    "category": "na"
  },
  {
    "question": "Never have I ever broken a bone.",
    "likes": 0,
    "category": "na"
  },
  {
    "question": "Never have I ever dropped my phone in the toilet.",
    "likes": 0,
    "category": "na"
  },
  {
    "question": "Never have I ever purchased a brand new car.",
    "likes": 0,
    "category": "na"
  },
  {
    "question": "Never have I ever given up on a DIY project before finishing.",
    "likes": 0,
    "category": "na"
  },
  {
    "question": "Never have I ever kept a plant alive for longer than a year.",
    "likes": 0,
    "category": "na"
  },
  {
    "question": "Never have I ever spent the night in the hospital.",
    "likes": 0,
    "category": "na"
  },
  {
    "question": "Never have I ever been in a haunted house.",
    "likes": 0,
    "category": "na"
  },
  {
    "question": "Never have I ever faked \"connection issues\" to get out of working remotely.",
    "likes": 0,
    "category": "na"
  },
  {
    "question": "Never have I ever asked to speak to the manager.",
    "likes": 0,
    "category": "na"
  },
  {
    "question": "Never have I ever had a hair color that doesn't occur in nature ",
    "likes": 0,
    "category": "na"
  },
  {
    "question": "Never have I ever written a poem.",
    "likes": 0,
    "category": "na"
  },
  {
    "question": "Never have I ever painted a picture.",
    "likes": 0,
    "category": "na"
  },
  {
    "question": "Never have I ever performed on stage.",
    "likes": 0,
    "category": "na"
  },
  {
    "question": "Never have I ever built something from scratch.",
    "likes": 0,
    "category": "na"
  },
  {
    "question": "Never have I ever invented something.",
    "likes": 0,
    "category": "na"
  },
  {
    "question": "Never have I ever taken a dance class.",
    "likes": 0,
    "category": "na"
  },
  {
    "question": "Never have I ever learned to play a musical instrument.",
    "likes": 0,
    "category": "na"
  },
  {
    "question": "Never have I ever written a song.",
    "likes": 0,
    "category": "na"
  },
  {
    "question": "Never have I ever sewed my own clothes.",
    "likes": 0,
    "category": "na"
  },
  {
    "question": "Never have I ever tried pottery or ceramics.",
    "likes": 0,
    "category": "na"
  },
  {
    "question": "Never have I ever created a piece of art that I\u2019m really proud of.",
    "likes": 0,
    "category": "na"
  },
  {
    "question": "Never have I ever written a short story.",
    "likes": 0,
    "category": "na"
  },
  {
    "question": "Never have I ever taken part in a talent show.",
    "likes": 0,
    "category": "na"
  },
  {
    "question": "Never have I ever knitted or crocheted anything.",
    "likes": 0,
    "category": "na"
  },
  {
    "question": "Never have I ever attended an art exhibit.",
    "likes": 0,
    "category": "na"
  },
  {
    "question": "Never have I ever made a sculpture.",
    "likes": 0,
    "category": "na"
  },
  {
    "question": "Never have I ever sketched a portrait.",
    "likes": 0,
    "category": "na"
  },
  {
    "question": "Never have I ever designed a website or app.",
    "likes": 0,
    "category": "na"
  },
  {
    "question": "Never have I ever tried my hand at photography.",
    "likes": 0,
    "category": "na"
  },
  {
    "question": "Never have I ever created a YouTube video.",
    "likes": 0,
    "category": "na"
  },
  {
    "question": "Never have I ever choreographed a dance.",
    "likes": 0,
    "category": "na"
  },
  {
    "question": "Never have I ever taken a cooking or baking class.",
    "likes": 0,
    "category": "na"
  },
  {
    "question": "Never have I ever tried calligraphy.",
    "likes": 0,
    "category": "na"
  },
  {
    "question": "Never have I ever started a blog.",
    "likes": 0,
    "category": "na"
  },
  {
    "question": "Never have I ever made my own jewelry.",
    "likes": 0,
    "category": "na"
  },
  {
    "question": "Never have I ever drawn a comic or cartoon.",
    "likes": 0,
    "category": "na"
  },
  {
    "question": "Never have I ever recorded a podcast.",
    "likes": 0,
    "category": "na"
  },
  {
    "question": "Never have I ever designed a logo.",
    "likes": 0,
    "category": "na"
  },
  {
    "question": "Never have I ever created my own game.",
    "likes": 0,
    "category": "na"
  },
  {
    "question": "Never have I ever written a letter to my future self.",
    "likes": 0,
    "category": "na"
  },
  {
    "question": "Never have I ever made a handmade gift for someone.",
    "likes": 0,
    "category": "na"
  },
  {
    "question": "Never have I ever tried woodworking.",
    "likes": 0,
    "category": "na"
  },
  {
    "question": "Never have I ever painted a mural.",
    "likes": 0,
    "category": "na"
  },
  {
    "question": "Never have I ever made a DIY home decoration.",
    "likes": 0,
    "category": "na"
  },
  {
    "question": "Never have I ever upcycled something old into something new.",
    "likes": 0,
    "category": "na"
  },
  {
    "question": "Never have I ever taken an art class just for fun.",
    "likes": 0,
    "category": "na"
  },
  {
    "question": "Never have I ever performed in a street performance.",
    "likes": 0,
    "category": "na"
  },
  {
    "question": "Never have I ever acted in a play or film.",
    "likes": 0,
    "category": "na"
  },
  {
    "question": "Never have I ever learned a magic trick.",
    "likes": 0,
    "category": "na"
  },
  {
    "question": "Never have I ever ghosted someone after a date.",
    "likes": 0,
    "category": "na"
  },
  {
    "question": "Never have I ever lied to my doctor.",
    "likes": 0,
    "category": "na"
  },
  {
    "question": "Never have I ever donated blood.",
    "likes": 0,
    "category": "na"
  },
  {
    "question": "Never have I ever been in a physical fight.",
    "likes": 0,
    "category": "na"
  },
  {
    "question": "Never have I ever jumped into a pool with clothes on.",
    "likes": 0,
    "category": "na"
  },
  {
    "question": "Never have I ever hit a parked car.",
    "likes": 0,
    "category": "na"
  },
  { "question": "Never have I ever been on TV.", "likes": 0, "category": "na" },
  {
    "question": "Never have I ever been fired from a job.",
    "likes": 0,
    "category": "na"
  },
  {
    "question": "Never have I ever cut my own bangs.",
    "likes": 0,
    "category": "na"
  },
  {
    "question": "Never have I ever lied to someone about how cute their baby was.",
    "likes": 0,
    "category": "na"
  },
  {
    "question": "Never have I ever quit a job and walked out on the spot.",
    "likes": 0,
    "category": "na"
  },
  {
    "question": "Never have I ever been to a casino.",
    "likes": 0,
    "category": "na"
  },
  {
    "question": "Never have I ever been stung by a bee.",
    "likes": 0,
    "category": "na"
  },
  {
    "question": "Never have I ever gone snowboarding.",
    "likes": 0,
    "category": "na"
  },
  { "question": "Never have I ever fainted.", "likes": 0, "category": "na" },
  {
    "question": "Never have I ever ridden a motorcycle.",
    "likes": 0,
    "category": "na"
  },
  {
    "question": "Never have I ever cried at work.",
    "likes": 0,
    "category": "na"
  },
  {
    "question": "Never have I ever lied about how much money I made.",
    "likes": 0,
    "category": "na"
  },
  {
    "question": "Never have I ever gone skinny-dipping.",
    "likes": 0,
    "category": "na"
  },
  {
    "question": "Never have I ever had a crush on someone I worked with.",
    "likes": 0,
    "category": "na"
  },
  {
    "question": "Never have I ever lived alone..",
    "likes": 0,
    "category": "na"
  },
  {
    "question": "Never have I ever covered for a friend who was lying.",
    "likes": 0,
    "category": "na"
  },
  {
    "question": "Never have I ever eaten something bad that a significant other cooked because I didn't want to hurt their feelings.",
    "likes": 0,
    "category": "na"
  },
  {
    "question": "Never have I ever screamed during a scary movie.",
    "likes": 0,
    "category": "na"
  },
  {
    "question": "Never have I ever accidentally said \u201cI love you\u201d to a teacher or boss.",
    "likes": 0,
    "category": "na"
  },
  {
    "question": "Never have I ever TP\u2019d someone\u2019s house.",
    "likes": 0,
    "category": "na"
  },
  {
    "question": "Never have I ever pretended to be on the phone to avoid a situation or person.",
    "likes": 0,
    "category": "na"
  },
  {
    "question": "Never have I ever had an embarrassing pet name for a significant other.",
    "likes": 0,
    "category": "na"
  },
  {
    "question": "Never have I ever gotten food poisoning.",
    "likes": 0,
    "category": "na"
  },
  {
    "question": "Never have I ever cried at a kids' movie.",
    "likes": 0,
    "category": "na"
  },
  {
    "question": "Never have I ever pretended to look busy when my boss was paying attention.",
    "likes": 0,
    "category": "na"
  },
  {
    "question": "Never have I ever been hungover.",
    "likes": 0,
    "category": "na"
  },
  {
    "question": "Never have I ever crashed a wedding or party I wasn\u2019t invited to.",
    "likes": 0,
    "category": "na"
  },
  {
    "question": "Never have I ever gone more than two days without showering.",
    "likes": 0,
    "category": "na"
  },
  {
    "question": "Never have I ever used someone else\u2019s toothbrush.",
    "likes": 0,
    "category": "na"
  },
  {
    "question": "Never have I ever created a fake social media account.",
    "likes": 0,
    "category": "na"
  },
  {
    "question": "Never have I never secretly enjoyed a smell that other people find gross.",
    "likes": 0,
    "category": "na"
  },
  {
    "question": "Never have I ever eaten a whole carton of ice cream by myself.",
    "likes": 0,
    "category": "na"
  },
  {
    "question": "Never have I ever wished I were on a reality TV show.",
    "likes": 0,
    "category": "na"
  },
  {
    "question": "Never have I ever had a crush on a fictional character.",
    "likes": 0,
    "category": "na"
  },
  {
    "question": "Never have I ever lied to someone about their outfit looking good.",
    "likes": 0,
    "category": "na"
  },
  {
    "question": "Never have I ever been out in public with a visible booger in my nose.",
    "likes": 0,
    "category": "na"
  },
  {
    "question": "Never have I ever regifted something that was given to me.",
    "likes": 0,
    "category": "na"
  },
  {
    "question": "Never have I ever sung karaoke.",
    "likes": 0,
    "category": "na"
  },
  {
    "question": "Never have I ever cried because of a commercial.",
    "likes": 0,
    "category": "na"
  },
  {
    "question": "Never have I ever used someone else\u2019s Netflix login.",
    "likes": 0,
    "category": "na"
  },
  {
    "question": "Never have I ever lied while we\u2019ve been playing this game.",
    "likes": 0,
    "category": "na"
  },
  {
    "question": "Never have I ever made money illegally.",
    "likes": 0,
    "category": "na"
  },
  {
    "question": "Never have I ever faked an illness to stay home from work.",
    "likes": 0,
    "category": "na"
  },
  {
    "question": "Never have I ever Facebook stalked an ex.",
    "likes": 0,
    "category": "na"
  },
  {
    "question": "Never have I ever looked through my girlfriend/boyfriend\u2019s phone without their knowledge.",
    "likes": 0,
    "category": "na"
  },
  {
    "question": "Never have I ever jumped from an airplane.",
    "likes": 0,
    "category": "na"
  },
  {
    "question": "Never have I ever text while driving.",
    "likes": 0,
    "category": "na"
  },
  {
    "question": "Never have I ever spent time in jail.",
    "likes": 0,
    "category": "na"
  },
  {
    "question": "Never have I ever spent a night in the hospital.",
    "likes": 0,
    "category": "na"
  },
  {
    "question": "Never have I ever woken up in a strange place.",
    "likes": 0,
    "category": "na"
  },
  {
    "question": "Never have I ever forgotten where I left my car.",
    "likes": 0,
    "category": "na"
  },
  {
    "question": "Never have I ever purposely given someone the wrong directions.",
    "likes": 0,
    "category": "na"
  },
  {
    "question": "Never have I ever purposely given someone the wrong phone number.",
    "likes": 0,
    "category": "na"
  },
  {
    "question": "Never have I ever shaved my head bald.",
    "likes": 0,
    "category": "na"
  },
  {
    "question": "Never have I ever paid late fees on an overdue bill.",
    "likes": 0,
    "category": "na"
  },
  {
    "question": "Never have I ever fallen asleep in church.",
    "likes": 0,
    "category": "na"
  },
  {
    "question": "Never have I ever made a poor excuse to leave a party and got caught in the web of lies.",
    "likes": 0,
    "category": "na"
  },
  {
    "question": "Never have I ever lied about having an emergency to leave a bad date early.",
    "likes": 0,
    "category": "na"
  },
  {
    "question": "Never have I ever stuffed my pockets with food from a buffet to take home with me.",
    "likes": 0,
    "category": "na"
  },
  {
    "question": "Never have I ever taken store-bought food to a party as my side dish but passed it off as my own.",
    "likes": 0,
    "category": "na"
  },
  {
    "question": "Never have I ever worn someone else\u2019s underwear.",
    "likes": 0,
    "category": "na"
  },
  {
    "question": "Never have I ever bought something special to wear one time then return it when I was done with it.",
    "likes": 0,
    "category": "na"
  },
  {
    "question": "Never have I ever crashed a party.",
    "likes": 0,
    "category": "na"
  },
  {
    "question": "Never have I ever gone skinny dipping.",
    "likes": 0,
    "category": "explicit"
  },
  {
    "question": "Never have I ever kissed my best friend.",
    "likes": 0,
    "category": "explicit"
  },
  {
    "question": "Never have I ever slid into someone's DMs.",
    "likes": 0,
    "category": "explicit"
  },
  {
    "question": "Never have I ever had a crush on a teacher.",
    "likes": 0,
    "category": "explicit"
  },
  {
    "question": "Never have I ever been in love.",
    "likes": 0,
    "category": "explicit"
  },
  {
    "question": "Never have I ever made out in a public place.",
    "likes": 0,
    "category": "explicit"
  },
  {
    "question": "Never have I ever played spin the bottle.",
    "likes": 0,
    "category": "explicit"
  },
  {
    "question": "Never have I ever kissed a friend's ex.",
    "likes": 0,
    "category": "explicit"
  },
  {
    "question": "Never have I ever told someone \"I love you\" without meaning it.",
    "likes": 0,
    "category": "explicit"
  },
  {
    "question": "Never have I ever been called a player.",
    "likes": 0,
    "category": "explicit"
  },
  {
    "question": "Never have I ever given a lap dance.",
    "likes": 0,
    "category": "explicit"
  },
  {
    "question": "Never have I ever gotten a lap dance.",
    "likes": 0,
    "category": "explicit"
  },
  {
    "question": "Never have I ever kissed more than one person in 24 hours.",
    "likes": 0,
    "category": "explicit"
  },
  {
    "question": "Never have I ever cheated on someone.",
    "likes": 0,
    "category": "explicit"
  },
  {
    "question": "Never have I ever been cheated on.",
    "likes": 0,
    "category": "explicit"
  },
  {
    "question": "Never have I ever sent a racy text to the wrong person.",
    "likes": 0,
    "category": "explicit"
  },
  {
    "question": "Never have I ever played strip poker.",
    "likes": 0,
    "category": "explicit"
  },
  {
    "question": "Never have I ever been arrested.",
    "likes": 0,
    "category": "explicit"
  },
  {
    "question": "Never have I ever been expelled.",
    "likes": 0,
    "category": "explicit"
  },
  {
    "question": "Never have I ever stolen anything.",
    "likes": 0,
    "category": "explicit"
  },
  {
    "question": "Never have I ever gotten a hickey.",
    "likes": 0,
    "category": "explicit"
  },
  {
    "question": "Never have I ever been fired.",
    "likes": 0,
    "category": "explicit"
  },
  {
    "question": "Never have I ever made out in a cinema.",
    "likes": 0,
    "category": "explicit"
  },
  {
    "question": "Never have I ever had a friend with benefits.",
    "likes": 0,
    "category": "explicit"
  },
  {
    "question": "Never have I ever catfished someone.",
    "likes": 0,
    "category": "explicit"
  },
  {
    "question": "Never have I ever gone streaking.",
    "likes": 0,
    "category": "explicit"
  },
  {
    "question": "Never have I ever had a threesome",
    "likes": 0,
    "category": "explicit"
  },
  {
    "question": "Never have I ever left someone on read",
    "likes": 0,
    "category": "explicit"
  },
  {
    "question": "Never have I ever fallen asleep during sex",
    "likes": 0,
    "category": "explicit"
  },
  {
    "question": "Never have I ever had sex on a beach",
    "likes": 0,
    "category": "explicit"
  },
  {
    "question": "Never have I ever been nude in public.",
    "likes": 0,
    "category": "explicit"
  },
  {
    "question": "Never have I ever dated or hooked up with someone 10 years older.",
    "likes": 0,
    "category": "explicit"
  },
  {
    "question": "Never have I ever dated or hooked up with someone 5 years younger.",
    "likes": 0,
    "category": "explicit"
  },
  {
    "question": "Never have I ever flashed someone.",
    "likes": 0,
    "category": "explicit"
  },
  {
    "question": "Never have I ever mooned someone.",
    "likes": 0,
    "category": "explicit"
  },
  {
    "question": "Never have I ever cried or flirted my way out of a ticket.",
    "likes": 0,
    "category": "explicit"
  },
  {
    "question": "Never have I ever sent nudes.",
    "likes": 0,
    "category": "explicit"
  },
  {
    "question": "Never have I ever received nudes.",
    "likes": 0,
    "category": "explicit"
  },
  {
    "question": "Never have I ever been on a blind date.",
    "likes": 0,
    "category": "explicit"
  },
  {
    "question": "Never have I ever gotten or given a hickey.",
    "likes": 0,
    "category": "explicit"
  },
  {
    "question": "Never have I ever gotten a bedroom-related injury.",
    "likes": 0,
    "category": "explicit"
  },
  {
    "question": "Never have I ever paid for adult content.",
    "likes": 0,
    "category": "explicit"
  },
  {
    "question": "Never have I ever hooked up with someone of the same sex or gender.",
    "likes": 0,
    "category": "explicit"
  },
  {
    "question": "Never have I ever slid into an ex's DMs.",
    "likes": 0,
    "category": "explicit"
  },
  {
    "question": "Never have I ever flirted with a married person.",
    "likes": 0,
    "category": "explicit"
  },
  {
    "question": "Never have I ever sexted an ex.",
    "likes": 0,
    "category": "explicit"
  },
  {
    "question": "Never have I ever sent a sext to the wrong person.",
    "likes": 0,
    "category": "explicit"
  },
  {
    "question": "Never have I ever filmed an intimate moment.",
    "likes": 0,
    "category": "explicit"
  },
  {
    "question": "Never have I ever danced on a pole",
    "likes": 0,
    "category": "explicit"
  },
  {
    "question": "Never have I ever hooked up with a sibling's friend.",
    "likes": 0,
    "category": "explicit"
  },
  {
    "question": "Never have I ever hooked up with a friend's ex.",
    "likes": 0,
    "category": "explicit"
  },
  {
    "question": "Never have I ever hooked up with an ex's friend.",
    "likes": 0,
    "category": "explicit"
  },
  {
    "question": "Never have I ever kissed a stranger.",
    "likes": 0,
    "category": "explicit"
  },
  {
    "question": "Never have I ever been on a date with someone more than 20 years older than me.",
    "likes": 0,
    "category": "explicit"
  },
  {
    "question": "Never have I ever been in an open relationship.",
    "likes": 0,
    "category": "explicit"
  },
  {
    "question": "Never have I ever kissed someone on the first date.",
    "likes": 0,
    "category": "explicit"
  },
  {
    "question": "Never have I ever been kissed on the beach.",
    "likes": 0,
    "category": "explicit"
  },
  {
    "question": "Never have I ever snooped through a partner's things.",
    "likes": 0,
    "category": "explicit"
  },
  {
    "question": "Never have I ever had a one-night stand.",
    "likes": 0,
    "category": "explicit"
  },
  {
    "question": "Never have I ever kissed more than one person in the same 24 hours.",
    "likes": 0,
    "category": "explicit"
  },
  {
    "question": "Never have I ever sent a steamy text",
    "likes": 0,
    "category": "explicit"
  },
  {
    "question": "Never have I ever kissed on the first date.",
    "likes": 0,
    "category": "explicit"
  },
  {
    "question": "Never have I ever had sex on the first date.",
    "likes": 0,
    "category": "explicit"
  },
  {
    "question": "Never have I ever accidentally sent an inappropriate email to my boss",
    "likes": 0,
    "category": "explicit"
  }
]
